itptest/__init__.py
itptest/qwe.py
itptest-0.1.0.dist-info/WHEEL
itptest-0.1.0.dist-info/METADATA
itptest-0.1.0.dist-info/RECORD
