Metadata-Version: 2.1
Name: itptest
Version: 0.1.0
Summary: 
Author: kirshuvl
Author-email: kirshuvl@gmail.com
Requires-Python: >=3.10,<4.0
Classifier: Programming Language :: Python :: 3
Classifier: Programming Language :: Python :: 3.10
Requires-Dist: fastapi (>=0.116.1,<0.117.0)
